boring_theme/404.html
boring_theme/__init__.py
boring_theme/base.html
boring_theme/main.html
boring_theme/mkdocs_theme.yml
boring_theme/nav.html
boring_theme/search.html
boring_theme/css/boring.css
boring_theme/css/theme.css
boring_theme/js/formatting.js
boring_theme/js/theme.js
mkdocs_boring_theme-0.1.11.dist-info/LICENSE
mkdocs_boring_theme-0.1.11.dist-info/METADATA
mkdocs_boring_theme-0.1.11.dist-info/WHEEL
mkdocs_boring_theme-0.1.11.dist-info/entry_points.txt
mkdocs_boring_theme-0.1.11.dist-info/top_level.txt
mkdocs_boring_theme-0.1.11.dist-info/RECORD
