Metadata-Version: 2.1
Name: mkdocs-boring-theme
Version: 0.1.11
Summary: Boring MkDocs theme based on CSS framework Min (mincss.com)
Home-page: https://resing.dev/mkdocs-boring-theme/
Author: Max Resing
Author-email: max.resing@protonmail.com
License: MIT
Project-URL: Source, https://codeberg.org/resingm/mkdocs-boring-theme
Project-URL: Tracker, https://codeberg.org/resingm/mkdocs-boring-theme/issues
Platform: UNKNOWN
Requires-Python: >=3.7
License-File: LICENSE
Requires-Dist: mkdocs (>=1.1)
